anymotion_cli/__init__.py
anymotion_cli/click_custom/__init__.py
anymotion_cli/click_custom/core.py
anymotion_cli/click_custom/decorators.py
anymotion_cli/click_custom/didyoumean.py
anymotion_cli/click_custom/formatting.py
anymotion_cli/click_custom/global_help.py
anymotion_cli/click_custom/help_colors.py
anymotion_cli/click_custom/repl.py
anymotion_cli/commands/__init__.py
anymotion_cli/commands/analysis.py
anymotion_cli/commands/analyze.py
anymotion_cli/commands/compare.py
anymotion_cli/commands/comparison.py
anymotion_cli/commands/configure.py
anymotion_cli/commands/download.py
anymotion_cli/commands/draw.py
anymotion_cli/commands/drawing.py
anymotion_cli/commands/extract.py
anymotion_cli/commands/image.py
anymotion_cli/commands/interactive.py
anymotion_cli/commands/keypoint.py
anymotion_cli/commands/movie.py
anymotion_cli/commands/upload.py
anymotion_cli/config.py
anymotion_cli/core.py
anymotion_cli/exceptions.py
anymotion_cli/options.py
anymotion_cli/output.py
anymotion_cli/settings.py
anymotion_cli/state.py
anymotion_cli/utils.py
anymotion_cli-1.3.2.dist-info/entry_points.txt
anymotion_cli-1.3.2.dist-info/LICENSE
anymotion_cli-1.3.2.dist-info/WHEEL
anymotion_cli-1.3.2.dist-info/METADATA
anymotion_cli-1.3.2.dist-info/RECORD
