Metadata-Version: 2.1
Name: anymotion-cli
Version: 1.3.2
Summary: Command Line Interface for AnyMotion API
Home-page: https://github.com/nttpc/anymotion-cli
License: MIT
Author: Yusuke Kumihashi
Author-email: y_kumiha@nttpc.co.jp
Requires-Python: >=3.6.1,<4.0.0
Classifier: License :: OSI Approved :: MIT License
Classifier: Programming Language :: Python :: 3
Classifier: Programming Language :: Python :: 3.10
Classifier: Programming Language :: Python :: 3.6
Classifier: Programming Language :: Python :: 3.7
Classifier: Programming Language :: Python :: 3.8
Classifier: Programming Language :: Python :: 3.9
Requires-Dist: anymotion-sdk (>=1.2.7)
Requires-Dist: click (>=7.1,<8.0)
Requires-Dist: importlib_metadata (>=4.0,<5.0); python_version < "3.8"
Requires-Dist: prompt-toolkit (>=3.0.7,<4.0.0)
Requires-Dist: pygments (>=2.6.1,<3.0.0)
Requires-Dist: requests (>=2.25.0,<3.0.0)
Requires-Dist: tabulate (>=0.8.6,<0.9.0)
Requires-Dist: yaspin (>=1.2,<2.0)
Project-URL: Repository, https://github.com/nttpc/anymotion-cli
